BigChars/__init__.py
Banner_9000-1.0.1.dist-info/LICENSE
Banner_9000-1.0.1.dist-info/METADATA
Banner_9000-1.0.1.dist-info/WHEEL
Banner_9000-1.0.1.dist-info/top_level.txt
Banner_9000-1.0.1.dist-info/RECORD
