Metadata-Version: 2.1
Name: Banner-9000
Version: 1.0.1
Summary: Big-Character Banner Printer
Author-email: Randall Nagy <r.a.nagy@gmail.com>
Project-URL: Homepage, https://github.com/soft9000/Banner9000
Project-URL: Bug Tracker, https://github.com/soft9000/Banner9000/issues
Classifier: Programming Language :: Python :: 3
Classifier: License :: OSI Approved :: MIT License
Classifier: Operating System :: OS Independent
Requires-Python: >=3.6
License-File: LICENSE
